yanf/__init__.py
yanf/yanflib/__init__.py
yanf/yanflib/formatter.py
yanf-0.0.2.dist-info/METADATA
yanf-0.0.2.dist-info/WHEEL
yanf-0.0.2.dist-info/entry_points.txt
yanf-0.0.2.dist-info/top_level.txt
yanf-0.0.2.dist-info/RECORD
